{
  "sim_config": {
    "alternative_full_space_mesh": "",
    "integrator_config": {
      "ae_decoded_dim": 83,
      "ae_encoded_dim": 15,
      "gravity": -9.8,
      "gravity_axis": 1,
      "lbfgs_config": {
        "lbfgs_epsilon": 1e-08,
        "lbfgs_m": 8,
        "lbfgs_max_iterations": 10000
      },
      "pca_dim": 83,
      "quasi_static": false,
      "reduced_energy_method": "an08_all",
      "reduced_space_type": "linear",
      "save_obj_every_iteration": false,
      "start_pose_from_training_data": -1,
      "timestep": 0.005,
      "use_partial_decode": true,
      "use_preconditioner": true,
      "use_reduced_energy": false
    },
    "logging_enabled": true,
    "material_config": {
      "density": 1000,
      "poissons_ratio": 0.47,
      "youngs_modulus": 30000
    },
    "mesh": "models/armadillo_high_limb_interaction/tets.mesh",
    "save_objs": false,
    "save_training_data_path": "",
    "visualization_config": {
      "fixed_point_constraint": [
        0,
        0.124,
        -0.1
      ],
      "fixed_point_radius": 0.11,
      "flip_constrained_axis": false,
      "full_space_constrained_axis": -1,
      "gpu_decode": true,
      "interaction_spring_stiffness": 10,
      "max_frames": 0,
      "print_every_n_frames": 1,
      "show_energy": false,
      "show_stress": false,
      "spring_grab_radius": 0.03
    }
  },
  "timesteps": [
    {
      "current_frame": 0,
      "iteration_info": {
        "lbfgs_iteration": [
          0,
          1
        ],
        "lbfgs_line_iteration": [
          0,
          0
        ],
        "lbfgs_obj_vals": [
          0.0,
          -2.30717871439836e-08
        ]
      },
      "lbfgs_iterations": 1,
      "mouse_info": {
        "dragged_mesh_pos": [
          0.0,
          0.0,
          0.0
        ],
        "dragged_pos": [
          0.0,
          0.0,
          0.0
        ],
        "is_dragging": false
      },
      "precondition_time": 7.15255737304688e-07,
      "tot_step_time_s": 0.227014780044556
    },
    {
      "current_frame": 1,
      "iteration_info": {
        "lbfgs_iteration": [
          0,
          1,
          2
        ],
        "lbfgs_line_iteration": [
          0,
          0,
          0
        ],
        "lbfgs_obj_vals": [
          6.92153688768851e-08,
          -1.12477307041453e-08,
          -1.12491434383791e-08
        ]
      },
      "lbfgs_iterations": 2,
      "mouse_info": {
        "dragged_mesh_pos": [
          0.0,
          0.0,
          0.0
        ],
        "dragged_pos": [
          0.0,
          0.0,
          0.0
        ],
        "is_dragging": false
      },
      "precondition_time": 4.76837158203125e-07,
      "tot_step_time_s": 0.258309364318848
    },
    {
      "current_frame": 2,
      "iteration_info": {
        "lbfgs_iteration": [
          0,
          1,
          2
        ],
        "lbfgs_line_iteration": [
          0,
          0,
          0
        ],
        "lbfgs_obj_vals": [
          1.72880121798225e-07,
          1.58877385518348e-08,
          1.588038287662e-08
        ]
      },
      "lbfgs_iterations": 2,
      "mouse_info": {
        "dragged_mesh_pos": [
          0.0,
          0.0,
          0.0
        ],
        "dragged_pos": [
          0.0,
          0.0,
          0.0
        ],
        "is_dragging": false
      },
      "precondition_time": 1.19209289550781e-06,
      "tot_step_time_s": 0.249272346496582
    },
    {
      "current_frame": 3,
      "iteration_info": {
        "lbfgs_iteration": [
          0,
          1,
          2
        ],
        "lbfgs_line_iteration": [
          0,
          0,
          0
        ],
        "lbfgs_obj_vals": [
          3.03285882822456e-07,
          6.39600990566352e-08,
          6.39341023132385e-08
        ]
      },
      "lbfgs_iterations": 2,
      "mouse_info": {
        "dragged_mesh_pos": [
          0.0,
          0.0,
          0.0
        ],
        "dragged_pos": [
          0.0,
          0.0,
          0.0
        ],
        "is_dragging": false
      },
      "precondition_time": 7.15255737304688e-07,
      "tot_step_time_s": 0.253647804260254
    },
    {
      "current_frame": 4,
      "iteration_info": {
        "lbfgs_iteration": [
          0,
          1,
          2
        ],
        "lbfgs_line_iteration": [
          0,
          0,
          0
        ],
        "lbfgs_obj_vals": [
          4.52888566735813e-07,
          1.35180083695256e-07,
          1.35069937080572e-07
        ]
      },
      "lbfgs_iterations": 2,
      "mouse_info": {
        "dragged_mesh_pos": [
          0.0,
          0.0,
          0.0
        ],
        "dragged_pos": [
          0.0,
          0.0,
          0.0
        ],
        "is_dragging": false
      },
      "precondition_time": 4.76837158203125e-07,
      "tot_step_time_s": 0.252000331878662
    },
    {
      "current_frame": 5,
      "iteration_info": {
        "lbfgs_iteration": [
          0,
          1,
          2,
          3,
          4
        ],
        "lbfgs_line_iteration": [
          0,
          0,
          0,
          0,
          0
        ],
        "lbfgs_obj_vals": [
          6.14481169104758e-07,
          2.28564710699522e-07,
          2.28143760757603e-07,
          2.28121070932644e-07,
          2.281202065198e-07
        ]
      },
      "lbfgs_iterations": 4,
      "mouse_info": {
        "dragged_mesh_pos": [
          0.0,
          0.0,
          0.0
        ],
        "dragged_pos": [
          0.0,
          0.0,
          0.0
        ],
        "is_dragging": false
      },
      "precondition_time": 7.15255737304688e-07,
      "tot_step_time_s": 0.382539987564087
    },
    {
      "current_frame": 6,
      "iteration_info": {
        "lbfgs_iteration": [
          0,
          1,
          2,
          3,
          4,
          5
        ],
        "lbfgs_line_iteration": [
          0,
          0,
          0,
          0,
          0,
          0
        ],
        "lbfgs_obj_vals": [
          7.81370478199282e-07,
          3.41045257732274e-07,
          3.39779092540079e-07,
          3.39493793587127e-07,
          3.39480055170989e-07,
          3.39478295996305e-07
        ]
      },
      "lbfgs_iterations": 5,
      "mouse_info": {
        "dragged_mesh_pos": [
          0.0,
          0.0,
          0.0
        ],
        "dragged_pos": [
          0.0,
          0.0,
          0.0
        ],
        "is_dragging": false
      },
      "precondition_time": 7.15255737304688e-07,
      "tot_step_time_s": 0.473931074142456
    },
    {
      "current_frame": 7,
      "iteration_info": {
        "lbfgs_iteration": [
          0,
          1,
          2,
          3,
          4,
          5,
          6,
          7
        ],
        "lbfgs_line_iteration": [
          0,
          0,
          0,
          0,
          0,
          0,
          0,
          0
        ],
        "lbfgs_obj_vals": [
          9.48095414187358e-07,
          4.69705464005526e-07,
          4.67390078886236e-07,
          4.65176586625554e-07,
          4.65069462536571e-07,
          4.65031577994204e-07,
          4.65027401195008e-07,
          4.6502703464357e-07
        ]
      },
      "lbfgs_iterations": 7,
      "mouse_info": {
        "dragged_mesh_pos": [
          0.0,
          0.0,
          0.0
        ],
        "dragged_pos": [
          0.0,
          0.0,
          0.0
        ],
        "is_dragging": false
      },
      "precondition_time": 9.5367431640625e-07,
      "tot_step_time_s": 0.572871923446655
    },
    {
      "current_frame": 8,
      "iteration_info": {
        "lbfgs_iteration": [
          0,
          1,
          2,
          2,
          3,
          4,
          5,
          6,
          7,
          8
        ],
        "lbfgs_line_iteration": [
          0,
          0,
          0,
          1,
          0,
          0,
          0,
          0,
          0,
          0
        ],
        "lbfgs_obj_vals": [
          1.1100710226951e-06,
          6.11666597422522e-07,
          6.12113134242562e-07,
          6.02996482549332e-07,
          6.00844621453703e-07,
          6.00111032103499e-07,
          5.99942284405723e-07,
          5.99906102859265e-07,
          5.99897491952964e-07,
          5.99896417332333e-07
        ]
      },
      "lbfgs_iterations": 8,
      "mouse_info": {
        "dragged_mesh_pos": [
          0.0,
          0.0,
          0.0
        ],
        "dragged_pos": [
          0.0,
          0.0,
          0.0
        ],
        "is_dragging": false
      },
      "precondition_time": 4.76837158203125e-07,
      "tot_step_time_s": 0.718675851821899
    },
    {
      "current_frame": 9,
      "iteration_info": {
        "lbfgs_iteration": [
          0,
          1,
          2,
          2,
          3,
          4,
          5,
          6,
          7,
          8,
          9
        ],
        "lbfgs_line_iteration": [
          0,
          0,
          0,
          1,
          0,
          0,
          0,
          0,
          0,
          0,
          0
        ],
        "lbfgs_obj_vals": [
          1.26368891461514e-06,
          7.63812110316197e-07,
          7.82122469831655e-07,
          7.47428512679775e-07,
          7.42697008524178e-07,
          7.3976402647486e-07,
          7.38939529474636e-07,
          7.38738674693519e-07,
          7.38631330185108e-07,
          7.38613544601562e-07,
          7.38608173920282e-07
        ]
      },
      "lbfgs_iterations": 9,
      "mouse_info": {
        "dragged_mesh_pos": [
          0.0,
          0.0,
          0.0
        ],
        "dragged_pos": [
          0.0,
          0.0,
          0.0
        ],
        "is_dragging": false
      },
      "precondition_time": 7.15255737304688e-07,
      "tot_step_time_s": 0.845831394195557
    },
    {
      "current_frame": 10,
      "iteration_info": {
        "lbfgs_iteration": [
          0,
          1,
          2,
          2,
          3,
          4,
          5,
          6,
          7,
          8,
          9,
          10,
          11,
          12
        ],
        "lbfgs_line_iteration": [
          0,
          0,
          0,
          1,
          0,
          0,
          0,
          0,
          0,
          0,
          0,
          0,
          0,
          0
        ],
        "lbfgs_obj_vals": [
          1.40616146589332e-06,
          9.22674972932243e-07,
          9.90253071437743e-07,
          8.97295652076901e-07,
          8.89166766165509e-07,
          8.80483912433769e-07,
          8.76588820927195e-07,
          8.76006684411423e-07,
          8.75348051652204e-07,
          8.7519095126907e-07,
          8.75148496051736e-07,
          8.75134621819639e-07,
          8.75128709125307e-07,
          8.75128007655857e-07
        ]
      },
      "lbfgs_iterations": 12,
      "mouse_info": {
        "dragged_mesh_pos": [
          0.0,
          0.0,
          0.0
        ],
        "dragged_pos": [
          0.0,
          0.0,
          0.0
        ],
        "is_dragging": false
      },
      "precondition_time": 7.15255737304688e-07,
      "tot_step_time_s": 1.00462937355042
    },
    {
      "current_frame": 11,
      "iteration_info": {
        "lbfgs_iteration": [
          0,
          1,
          2,
          2,
          3,
          4,
          5,
          6,
          7,
          8,
          9,
          10,
          11,
          12,
          13,
          14,
          14
        ],
        "lbfgs_line_iteration": [
          0,
          0,
          0,
          1,
          0,
          0,
          0,
          0,
          0,
          0,
          0,
          0,
          0,
          0,
          0,
          0,
          1
        ],
        "lbfgs_obj_vals": [
          1.5357405800593e-06,
          1.08499442717745e-06,
          1.24511279043376e-06,
          1.05066338979413e-06,
          1.04439724587597e-06,
          1.02551930598913e-06,
          1.00864953686759e-06,
          1.00653323418566e-06,
          1.00545135430547e-06,
          1.00423376197187e-06,
          1.00395795571225e-06,
          1.00385733700831e-06,
          1.00383534231409e-06,
          1.00381777819389e-06,
          1.00381450667845e-06,
          1.0038150433181e-06,
          1.00381264667965e-06
        ]
      },
      "lbfgs_iterations": 14,
      "mouse_info": {
        "dragged_mesh_pos": [
          0.0,
          0.0,
          0.0
        ],
        "dragged_pos": [
          0.0,
          0.0,
          0.0
        ],
        "is_dragging": false
      },
      "precondition_time": 4.76837158203125e-07,
      "tot_step_time_s": 1.23046040534973
    },
    {
      "current_frame": 12,
      "iteration_info": {
        "lbfgs_iteration": [
          0,
          1,
          2,
          2,
          3,
          3,
          4,
          4,
          5,
          6,
          7,
          8,
          8,
          9,
          10,
          11,
          12,
          13,
          13,
          14,
          14,
          15,
          15,
          16,
          17
        ],
        "lbfgs_line_iteration": [
          0,
          0,
          0,
          1,
          0,
          1,
          0,
          1,
          0,
          0,
          0,
          0,
          1,
          0,
          0,
          0,
          0,
          0,
          1,
          0,
          1,
          0,
          1,
          0,
          0
        ],
        "lbfgs_obj_vals": [
          1.6506227853353e-06,
          1.24882837402535e-06,
          1.53579507856274e-06,
          1.20200710222279e-06,
          1.21485334939492e-06,
          1.15993884685874e-06,
          1.18672900671099e-06,
          1.13181422766357e-06,
          1.1250746409689e-06,
          1.1213255960604e-06,
          1.12004221394305e-06,
          1.12106174176286e-06,
          1.11976700526237e-06,
          1.1195585013847e-06,
          1.11951137072434e-06,
          1.11947288222673e-06,
          1.11945392812419e-06,
          1.11946241357645e-06,
          1.11945023413246e-06,
          1.11945052888928e-06,
          1.11944678951344e-06,
          1.11944739351312e-06,
          1.11944572279607e-06,
          1.1194455660871e-06,
          1.11944503687012e-06
        ]
      },
      "lbfgs_iterations": 17,
      "mouse_info": {
        "dragged_mesh_pos": [
          0.0,
          0.0,
          0.0
        ],
        "dragged_pos": [
          0.0,
          0.0,
          0.0
        ],
        "is_dragging": false
      },
      "precondition_time": 7.15255737304688e-07,
      "tot_step_time_s": 1.91441965103149
    },
    {
      "current_frame": 13,
      "iteration_info": {
        "lbfgs_iteration": [
          0,
          1,
          2,
          2,
          3,
          3,
          4,
          4,
          5,
          6,
          7,
          8,
          9,
          10,
          11,
          12,
          12,
          13,
          13,
          14,
          14,
          15,
          16,
          17,
          17,
          18
        ],
        "lbfgs_line_iteration": [
          0,
          0,
          0,
          1,
          0,
          1,
          0,
          1,
          0,
          0,
          0,
          0,
          0,
          0,
          0,
          0,
          1,
          0,
          1,
          0,
          1,
          0,
          0,
          0,
          1,
          0
        ],
        "lbfgs_obj_vals": [
          1.75094706408991e-06,
          1.41628461289685e-06,
          1.84771904155881e-06,
          1.34712469984651e-06,
          1.36542811961263e-06,
          1.28334936508179e-06,
          1.48823728965612e-06,
          1.25796892596041e-06,
          1.22942404955264e-06,
          1.22757662685681e-06,
          1.22337419194358e-06,
          1.21959666864328e-06,
          1.21892955260216e-06,
          1.21860535873575e-06,
          1.21853312770939e-06,
          1.21859527327329e-06,
          1.2185057245785e-06,
          1.21851765923484e-06,
          1.21848419195215e-06,
          1.2185040811027e-06,
          1.21846839621042e-06,
          1.21844787581555e-06,
          1.21843558837383e-06,
          