{
  "sim_config": {
    "alternative_full_space_mesh": "",
    "integrator_config": {
      "ae_decoded_dim": 0,
      "ae_encoded_dim": 0,
      "gravity": -9.8,
      "gravity_axis": 1,
      "lbfgs_config": {
        "lbfgs_delta": 1e-08,
        "lbfgs_delta_past": 0,
        "lbfgs_epsilon": 1e-07,
        "lbfgs_m": 8,
        "lbfgs_max_iterations": 500
      },
      "pca_dim": 0,
      "quasi_static": false,
      "reduced_energy_method": "full",
      "reduced_space_type": "full",
      "save_obj_every_iteration": false,
      "start_pose_from_training_data": -1,
      "timestep": 0.005,
      "use_partial_decode": false,
      "use_preconditioner": true,
      "use_reduced_energy": false
    },
    "logging_enabled": true,
    "material_config": {
      "density": 1000,
      "poissons_ratio": 0.47,
      "youngs_modulus": 60000
    },
    "mesh": "meshes/X_25cm_very_high.mesh",
    "png_scale": 2,
    "save_objs": false,
    "save_pngs": false,
    "save_training_data": true,
    "save_training_data_path": "models/X/unified_generate/high_res/training_data/training/",
    "visualization_config": {
      "camera_zoom": 1.47338,
      "constrained_axis_eps": 0.001,
      "fixed_point_constraint": [
        0,
        0.124,
        -0.1
      ],
      "fixed_point_radius": -1,
      "flip_constrained_axis": false,
      "full_space_constrained_axis": 1,
      "gpu_decode": false,
      "interaction_spring_stiffness": 30,
      "line_width": 1.5,
      "max_frames": 0,
      "print_every_n_frames": 1,
      "show_energy": false,
      "show_lines": true,
      "show_stress": false,
      "spring_grab_radius": 0.03,
      "trackball_angle": [
        0.931922,
        0.247646,
        0.256052,
        0.0680424
      ]
    }
  },
  "timesteps": [
    {
      "current_frame": 0,
      "iteration_info": {
        "lbfgs_iteration": [
          0,
          1
        ],
        "lbfgs_line_iteration": [
          0,
          0
        ],
        "lbfgs_obj_vals": [
          0.0,
          -2.2849631339467883e-08
        ],
        "timing": {
          "energy_forces_time_s": [
            0.040036916732788086,
            0.018862009048461914
          ],
          "linear_decode_time_s": [
            9.846687316894531e-05,
            0.0001010894775390625
          ],
          "obj_and_grad_eval_time_s": [
            0.00196075439453125,
            0.0015287399291992188
          ],
          "predict_weight_time": [
            0.0,
            0.0
          ],
          "tf_time_s": [
            3.9577484130859375e-05,
            3.314018249511719e-05
          ],
          "tot_obj_time_s": [
            0.042138099670410156,
            0.020528316497802734
          ]
        }
      },
      "lbfgs_iterations": 1,
      "mouse_info": {
        "dragged_mesh_pos": [
          0.0,
          0.0,
          0.0
        ],
        "dragged_pos": [
          0.0,
          0.0,
          0.0
        ],
        "is_dragging": false
      },
      "precondition_time": 0.6069936752319336,
      "tot_step_time_s": 0.6834549903869629
    },
    {
      "current_frame": 1,
      "iteration_info": {
        "lbfgs_iteration": [
          0,
          1,
          2
        ],
        "lbfgs_line_iteration": [
          0,
          0,
          0
        ],
        "lbfgs_obj_vals": [
          6.85736604632461e-08,
          -2.1993420765536816e-09,
          -2.1996204478376395e-09
        ],
        "timing": {
          "energy_forces_time_s": [
            0.034862518310546875,
            0.025288820266723633,
            0.03400731086730957
          ],
          "linear_decode_time_s": [
            0.00011229515075683594,
            0.00012350082397460938,
            9.226799011230469e-05
          ],
          "obj_and_grad_eval_time_s": [
            0.0025992393493652344,
            0.0023009777069091797,
            0.002080678939819336
          ],
          "predict_weight_time": [
            0.0,
            0.0,
            0.0
          ],
          "tf_time_s": [
            4.57763671875e-05,
            3.933906555175781e-05,
            2.6941299438476563e-05
          ],
          "tot_obj_time_s": [
            0.03762197494506836,
            0.027755022048950195,
            0.0362091064453125
          ]
        }
      },
      "lbfgs_iterations": 2,
      "mouse_info": {
        "dragged_mesh_pos": [
          0.0,
          0.0,
          0.0
        ],
        "dragged_pos": [
          0.0,
          0.0,
          0.0
        ],
        "is_dragging": false
      },
      "precondition_time": 0.5643861293792725,
      "tot_step_time_s": 0.6884384155273438
    },
    {
      "current_frame": 2,
      "iteration_info": {
        "lbfgs_iteration": [
          0,
          1,
          2
        ],
        "lbfgs_line_iteration": [
          0,
          0,
          0
        ],
        "lbfgs_obj_vals": [
          1.6157781856546532e-07,
          3.9898004523092885e-08,
          3.989713820072827e-08
        ],
        "timing": {
          "energy_forces_time_s": [
            0.03617095947265625,
            0.027431249618530273,
            0.02578115463256836
          ],
          "linear_decode_time_s": [
            8.296966552734375e-05,
            8.20159912109375e-05,
            7.939338684082031e-05
          ],
          "obj_and_grad_eval_time_s": [
            0.0017914772033691406,
            0.0016205310821533203,
            0.0016372203826904297
          ],
          "predict_weight_time": [
            0.0,
            0.0,
            0.0
          ],
          "tf_time_s": [
            4.57763671875e-05,
            2.956390380859375e-05,
            3.075599670410156e-05
          ],
          "tot_obj_time_s": [
            0.03809380531311035,
            0.02916550636291504,
            0.027530670166015625
          ]
        }
      },
      "lbfgs_iterations": 2,
      "mouse_info": {
        "dragged_mesh_pos": [
          0.0,
          0.0,
          0.0
        ],
        "dragged_pos": [
          0.0,
          0.0,
          0.0
        ],
        "is_dragging": false
      },
      "precondition_time": 0.49820709228515625,
      "tot_step_time_s": 0.6132028102874756
    },
    {
      "current_frame": 3,
      "iteration_info": {
        "lbfgs_iteration": [
          0,
          1,
          2
        ],
        "lbfgs_line_iteration": [
          0,
          0,
          0
        ],
        "lbfgs_obj_vals": [
          2.680096910456316e-07,
          1.0901815177696818e-07,
          1.0901562883665269e-07
        ],
        "timing": {
          "energy_forces_time_s": [
            0.029560327529907227,
            0.019000530242919922,
            0.021837711334228516
          ],
          "linear_decode_time_s": [
            9.632110595703125e-05,
            7.605552673339844e-05,
            6.67572021484375e-05
          ],
          "obj_and_grad_eval_time_s": [
            0.0015866756439208984,
            0.0016551017761230469,
            0.001613616943359375
          ],
          "predict_weight_time": [
            0.0,
            0.0,
            0.0
          ],
          "tf_time_s": [
            4.76837158203125e-05,
            2.6702880859375e-05,
            1.9550323486328125e-05
          ],
          "tot_obj_time_s": [
            0.031293392181396484,
            0.020760774612426758,
            0.02353978157043457
          ]
        }
      },
      "lbfgs_iterations": 2,
      "mouse_info": {
        "dragged_mesh_pos": [
          0.0,
          0.0,
          0.0
        ],
        "dragged_pos": [
          0.0,
          0.0,
          0.0
        ],
        "is_dragging": false
      },
      "precondition_time": 0.5022509098052979,
      "tot_step_time_s": 0.6003878116607666
    },
    {
      "current_frame": 4,
      "iteration_info": {
        "lbfgs_iteration": [
          0,
          1,
          2
        ],
        "lbfgs_line_iteration": [
          0,
          0,
          0
        ],
        "lbfgs_obj_vals": [
          3.771931176775857e-07,
          2.0136862468617916e-07,
          2.0136186871430672e-07
        ],
        "timing": {
          "energy_forces_time_s": [
            0.04520869255065918,
            0.030220508575439453,
            0.017449378967285156
          ],
          "linear_decode_time_s": [
            8.96453857421875e-05,
            8.106231689453125e-05,
            6.818771362304688e-05
          ],
          "obj_and_grad_eval_time_s": [
            0.0017914772033691406,
            0.0016129016876220703,
            0.0016236305236816406
          ],
          "predict_weight_time": [
            0.0,
            0.0,
            0.0
          ],
          "tf_time_s": [
            4.649162292480469e-05,
            2.3603439331054688e-05,
            1.52587890625e-05
          ],
          "tot_obj_time_s": [
            0.04713916778564453,
            0.031940460205078125,
            0.019158363342285156
          ]
        }
      },
      "lbfgs_iterations": 2,
      "mouse_info": {
        "dragged_mesh_pos": [
          0.0,
          0.0,
          0.0
        ],
        "dragged_pos": [
          0.0,
          0.0,
          0.0
        ],
        "is_dragging": false
      },
      "precondition_time": 0.51153564453125,
      "tot_step_time_s": 0.6312816143035889
    },
    {
      "current_frame": 5,
      "iteration_info": {
        "lbfgs_iteration": [
          0,
          1,
          2
        ],
        "lbfgs_line_iteration": [
          0,
          0,
          0
        ],
        "lbfgs_obj_vals": [
          4.796717520319222e-07,
          3.0457655877592273e-07,
          3.0455856208948516e-07
        ],
        "timing": {
          "energy_forces_time_s": [
            0.03991985321044922,
            0.02864980697631836,
            0.03125882148742676
          ],
          "linear_decode_time_s": [
            0.00011968612670898438,
            9.131431579589844e-05,
            6.699562072753906e-05
          ],
          "obj_and_grad_eval_time_s": [
            0.0030727386474609375,
            0.0017316341400146484,
            0.0020422935485839844
          ],
          "predict_weight_time": [
            0.0,
            0.0,
            0.0
          ],
          "tf_time_s": [
            4.124641418457031e-05,
            3.147125244140625e-05,
            2.6702880859375e-05
          ],
          "tot_obj_time_s": [
            0.04315543174743652,
            0.030506610870361328,
            0.03339695930480957
          ]
        }
      },
      "lbfgs_iterations": 2,
      "mouse_info": {
        "dragged_mesh_pos": [
          0.0,
          0.0,
          0.0
        ],
        "dragged_pos": [
          0.0,
          0.0,
          0.0
        ],
        "is_dragging": false
      },
      "precondition_time": 0.4966874122619629,
      "tot_step_time_s": 0.6269102096557617
    },
    {
      "current_frame": 6,
      "iteration_info": {
        "lbfgs_iteration": [
          0,
          1,
          2
        ],
        "lbfgs_line_iteration": [
          0,
          0,
          0
        ],
        "lbfgs_obj_vals": [
          5.680827008327472e-07,
          4.0336373215184746e-07,
          4.0332066761183786e-07
        ],
        "timing": {
          "energy_forces_time_s": [
            0.028712987899780273,
            0.028254270553588867,
            0.024459123611450195
          ],
          "linear_decode_time_s": [
            7.915496826171875e-05,
            8.440017700195313e-05,
            7.367134094238281e-05
          ],
          "obj_and_grad_eval_time_s": [
            0.0018444061279296875,
            0.0016529560089111328,
            0.0016520023345947266
          ],
          "predict_weight_time": [
            0.0,
            0.0,
            0.0
          ],
          "tf_time_s": [
            4.0531158447265625e-05,
            2.6464462280273438e-05,
            3.0040740966796875e-05
          ],
          "tot_obj_time_s": [
            0.030679702758789063,
            0.03002023696899414,
            0.026217937469482422
          ]
        }
      },
      "lbfgs_iterations": 2,
      "mouse_info": {
        "dragged_mesh_pos": [
          0.0,
          0.0,
          0.0
        ],
        "dragged_pos": [
          0.0,
          0.0,
          0.0
        ],
        "is_dragging": false
      },
      "precondition_time": 0.5118875503540039,
      "tot_step_time_s": 0.6151716709136963
    },
    {
      "current_frame": 7,
      "iteration_info": {
        "lbfgs_iteration": [
          0,
          1,
          2
        ],
        "lbfgs_line_iteration": [
          0,
          0,
          0
        ],
        "lbfgs_obj_vals": [
          6.377765598446106e-07,
          4.86133077713057e-07,
          4.860504590729834e-07
        ],
        "timing": {
          "energy_forces_time_s": [
            0.04178357124328613,
            0.028817415237426758,
            0.028011322021484375
          ],
          "linear_decode_time_s": [
            0.0001728534698486328,
            8.153915405273438e-05,
            8.96453857421875e-05
          ],
          "obj_and_grad_eval_time_s": [
            0.0021665096282958984,
            0.0017597675323486328,
            0.0012133121490478516
          ],
          "predict_weight_time": [
            0.0,
            0.0,
            0.0
          ],
          "tf_time_s": [
            0.0002949237823486328,
            1.8358230590820313e-05,
            2.2411346435546875e-05
          ],
          "tot_obj_time_s": [
            0.04442000389099121,
            0.03067922592163086,
            0.029338598251342773
          ]
        }
      },
      "lbfgs_iterations": 2,
      "mouse_info": {
        "dragged_mesh_pos": [
          0.0,
          0.0,
          0.0
        ],
        "dragged_pos": [
          0.0,
          0.0,
          0.0
        ],
        "is_dragging": false
      },
      "precondition_time": 0.5184464454650879,
      "tot_step_time_s": 0.6473281383514404
    },
    {
      "current_frame": 8,
      "iteration_info": {
        "lbfgs_iteration": [
          0,
          1,
          2
        ],
        "lbfgs_line_iteration": [
          0,
          0,
          0
        ],
        "lbfgs_obj_vals": [
          6.869646425569792e-07,
          5.486119056802653e-07,
          5.484895421421431e-07
        ],
        "timing": {
          "energy_forces_time_s": [
            0.042379140853881836,
            0.015723228454589844,
            0.017093896865844727
          ],
          "linear_decode_time_s": [
            9.274482727050781e-05,
            6.723403930664063e-05,
            7.033348083496094e-05
          ],
          "obj_and_grad_eval_time_s": [
            0.0019426345825195313,
            0.0015883445739746094,
            0.0015850067138671875
          ],
          "predict_weight_time": [
            0.0,
            0.0,
            0.0
          ],
          "tf_time_s": [
            4.458427429199219e-05,
            2.1696090698242188e-05,
            3.314018249511719e-05
          ],
          "tot_obj_time_s": [
            0.044461965560913086,
            0.017403602600097656,
            0.01878523826599121
          ]
        }
      },
      "lbfgs_iterations": 2,
      "mouse_info": {
        "dragged_mesh_pos": [
          0.0,
          0.0,
          0.0
        ],
        "dragged_pos": [
          0.0,
          0.0,
          0.0
        ],
        "is_dragging": false
      },
      "precondition_time": 0.4618246555328369,
      "tot_step_time_s": 0.5645558834075928
    },
    {
      "current_frame": 9,
      "iteration_info": {
        "lbfgs_iteration": [
          0,
          1,
          2,
          3
        ],
        "lbfgs_line_iteration": [
          0,
          0,
          0,
          0
        ],
        "lbfgs_obj_vals": [
          7.164282327819555e-07,
          5.932427343054018e-07,
          5.931032267983848e-07,
          5.93101227897348e-07
        ],
        "timing": {
          "energy_forces_time_s": [
            0.040694236755371094,
            0.0390477180480957,
            0.0304410457611084,
            0.029675006866455078
          ],
          "linear_decode_time_s": [
            0.00013566017150878906,
            7.081031799316406e-05,
            8.082389831542969e-05,
            5.91278076171875e-05
          ],
          "obj_and_grad_eval_time_s": [
            0.0022122859954833984,
            0.001790761947631836,
            0.0015985965728759766,
            0.0022194385528564453
          ],
          "predict_weight_time": [
            0.0,
            0.0,
            0.0,
            0.0
          ],
          "tf_time_s": [
            6.723403930664063e-05,
            1.7404556274414063e-05,
            1.8358230590820313e-05,
            1.0251998901367188e-05
          ],
          "tot_obj_time_s": [
            0.04311203956604004,
            0.04092907905578613,
            0.03214073181152344,
            0.0319666862487793
          ]
        }
      },
      "lbfgs_iterations": 3,
      "mouse_info": {
        "dragged_mesh_pos": [
          0.0,
          0.0,
          0.0
        ],
        "dragged_pos": [
          0.0,
          0.0,
          0.0
        ],
        "is_dragging": false
      },
      "precondition_time": 0.49301815032958984,
      "tot_step_time_s": 0.674107551574707
    },
    {
      "current_frame": 10,
      "iteration_info": {
        "lbfgs_iteration": [
          0,
          1,
          2
        ],
        "lbfgs_line_iteration": [
          0,
          0,
          0
        ],
        "lbfgs_obj_vals": [
          7.290682874382783e-07,
          6.255577750302211e-07,
          6.254354893184552e-07
        ],
        "timing": {
          "energy_forces_time_s": [
            0.01883840560913086,
            0.036753177642822266,
            0.03289389610290527
          ],
          "linear_decode_time_s": [
            0.00010204315185546875,
            0.0001308917999267578,
            0.0001270771026611328
          ],
          "obj_and_grad_eval_time_s": [
            0.0016312599182128906,
            0.0027151107788085938,
            0.002318859100341797
          ],
          "predict_weight_time": [
            0.0,
            0.0,
            0.0
          ],
          "tf_time_s": [
            3.910064697265625e-05,
            3.814697265625e-05,
            3.790855407714844e-05
          ],
          "tot_obj_time_s": [
            0.02061295509338379,
            0.039640188217163086,
            0.03538036346435547
          ]
        }
      },
      "lbfgs_iterations": 2,
      "mouse_info": {
        "dragged_mesh_pos": [
          0.0,
          0.0,
          0.0
        ],
        "dragged_pos": [
          0.0,
          0.0,
          0.0
        ],
        "is_dragging": false
      },
      "precondition_time": 0.498887300491333,
      "tot_step_time_s": 0.6227767467498779
    },
    {
      "current_frame": 11,
      "iteration_info": {
        "lbfgs_iteration": [
          0,
          1,
          2
        ],
        "lbfgs_line_iteration": [
          0,
          0,
          0
        ],
        "lbfgs_obj_vals": [
          7.285038317025151e-07,
          6.505473631901148e-07,
          6.504671054349459e-07
        ],
        "timing": {
          "energy_forces_time_s": [
            0.04914379119873047,
            0.03332638740539551,
            0.013429641723632813
          ],
          "linear_decode_time_s": [
            0.0001761913299560547,
            0.00017714500427246094,
            0.00010538101196289063
          ],
          "obj_and_grad_eval_time_s": [
            0.0027391910552978516,
            0.002211332321166992,
            0.002087116241455078
          ],
          "predict_weight_time": [
            0.0,
            0.0,
            0.0
          ],
          "tf_time_s": [
            7.009506225585938e-05,
            3.0279159545898438e-05,
            3.2901763916015625e-05
          ],
          "tot_obj_time_s": [
            0.05213189125061035,
            0.03574776649475098,
            0.01565718650817871
          ]
        }
      },
      "lbfgs_iterations": 2,
      "mouse_info": {
        "dragged_mesh_pos": [
          0.0,
          0.0,
          0.0
        ],
        "dragged_pos": [
          0.0,
          0.0,
          0.0
        ],
        "is_dragging": false
      },
      "precondition_time": 0.5219855308532715,
      "tot_step_time_s": 0.6453392505645752
    },
    {
      "current_frame": 12,
      "iteration_info": {
        "lbfgs_iteration": [
          0,
          1,
          2
        ],
        "lbfgs_line_iteration": [
          0,
          0,
          0
        ],
        "lbfgs_obj_vals": [
          7.19160598927579e-07,
          6.695969816154502e-07,
          6.695593852493495e-07
        ],
        "timing": {
          "energy_forces_time_s": [
            0.03730630874633789,
            0.031476736068725586,
            0.027155637741088867
          ],
          "linear_decode_time_s": [
            9.489059448242188e-05,
            0.00010561943054199219,
            9.417533874511719e-05
          ],
          "obj_and_grad_eval_time_s": [
            0.002017974853515625,
            0.001821279525756836,
            0.0016946792602539063
          ],
          "predict_weight_time": [
            0.0,
            0.0,
            0.0
          ],
          "tf_time_s": [
            4.458427429199219e-05,
            3.337860107421875e-05,
            3.0279159545898438e-05
          ],
          "tot_obj_time_s": [
            0.039465904235839844,
            0.033438920974731445,
            0.028977394104003906
          ]
        }
      },
      "lbfgs_iterations": 2,
      "mouse_info": {
        "dragged_mesh_pos": [
          0.0,
          0.0,
          0.0
        ],
        "dragged_pos": [
          0.0,
          0.0,
          0.0
        ],
        "is_dragging": false
      },
      "precondition_time": 0.49779820442199707,
      "tot_step_time_s": 0.6213529109954834
    },
    {
      "current_frame": 13,
      "iteration_info": {
        "lbfgs_iteration": [
          0,
          1,
          2
        ],
        "lbfgs_line_iteration": [
          0,
          0,
          0
        ],
        "lbfgs_obj_vals": [
          7.047362955445547e-07,
          6.808924780073874e-07,
          6.808813237257892e-07
        ],
        "timing": {
          "energy_forces_time_s": [
            0.038527488708496094,
            0.04650378227233887,
            0.014569759368896484
          ],
          "linear_decode_time_s": [
            0.0001862049102783203,
            0.00011014938354492188,
            0.00011873245239257813
          ],
          "obj_and_grad_eval_time_s": [
            0.002732992172241211,
            0.002169370651245117,
            0.002026081085205078
          ],
          "predict_weight_time": [
            0.0,
            0.0,
            0.0
          ],
          "tf_time_s": [
            5.841255187988281e-05,
            3.409385681152344e-05,
            3.4809112548828125e-05
          ],
          "tot_obj_time_s": [
            0.04150795936584473,
            0.04882001876831055,
            0.016751766204833984
          ]
        }
      },
      "lbfgs_iterations": 2,
      "mouse_info": {
        "dragged_mesh_pos": [
          0.0,
          0.0,
          0.0
        ],
        "dragged_pos": [
          0.0,
          0.0,
          0.0
        ],
        "is_dragging": false
      },
      "precondition_time": 0.5186941623687744,
      "tot_step_time_s": 0.6490991115570068
    },
    {
      "current_frame": 14,
      "iteration_info": {
        "lbfgs_iteration": [
          0,
          1,
          2
        ],
        "lbfgs_line_iteration": [
          0,
          0,
          0
        ],
        "lbfgs_obj_vals": [
          6.878374662619428e-07,
          6.812537689331329e-07,
          6.812522107675056e-07
        ],
        "timing": {
          "energy_forces_time_s": [
            0.025116920471191406,
            0.024251937866210938,
            0.03982710838317871
          ],
          "linear_decode_time_s": [
            8.654594421386719e-05,
            0.00014019012451171875,
            0.00012636184692382813
          ],
          "obj_and_grad_eval_time_s": [
            0.0016918182373046875,
            0.0033767223358154297,
            0.0027170181274414063
          ],
          "predict_weight_time": [
            0.0,
            0.0,
            0.0
          ],
          "tf_time_s": [
            4.100799560546875e-05,
            3.886222839355469e-05,
            3.3855438232421875e-05
          ],
          "tot_obj_time_s": [
            0.026938438415527344,
            0.027810335159301758,
            0.042707204818725586
          ]
        }
      },
      "lbfgs_iterations": 2,
      "mouse_info": {
        "dragged_mesh_pos": [
          0.0,
          0.0,
          0.0
        ],
        "dragged_pos": [
          0.0,
          0.0,
          0.0
        ],
        "is_dragging": false
      },
      "precondition_time": 0.49091434478759766,
      "tot_step_time_s": 0.6099863052368164
    },
    {
      "current_frame": 15,
      "iteration_info": {
        "lbfgs_iteration": [
          0,
          1
        ],
        "lbfgs_line_iteration": [
          0,
          0
        ],
        "lbfgs_obj_vals": [
          6.697505340885188e-07,
          6.684507719524016e-07
        ],
        "timing": {
          "energy_forces_time_s": [
            0.04245448112487793,
            0.028017520904541016
          ],
          "linear_decode_time_s": [
            0.00021457672119140625,
            8.654594421386719e-05
          ],
          "obj_and_grad_eval_time_s": [
            0.0020651817321777344,
            0.0017364025115966797
          ],
          "predict_weight_time": [
            0.0,
            0.0
          ],
          "tf_time_s": [
            7.581710815429688e-05,
            3.814697265625e-05
          ],
          "tot_obj_time_s": [
            0.04481244087219238,
            0.029880762100219727
          ]
        }
      },
      "lbfgs_iterations": 1,
      "mouse_info": {
        "dragged_mesh_pos": [
          0.0,
          0.0,
          0.0
        ],
        "dragged_pos": [
          0.0,
          0.0,
          0.0
        ],
        "is_dragging": false
      },
      "precondition_time": 0.6359353065490723,
      "tot_step_time_s": 0.7204794883728027
    },
    {
      "current_frame": 16,
      "iteration_info": {
        "lbfgs_iteration": [
          0,
          1,
          2
        ],
        "lbfgs_line_iteration": [
          0,
          0,
          0
        ],
        "lbfgs_obj_vals": [
          6.505487871824556e-07,
          6.426149552988294e-07,
          6.426131873267149e-07
        ],
        "timing": {
          "energy_forces_time_s": [
            0.03387451171875,
            0.03298592567443848,
            0.026212453842163086
          ],
          "linear_decode_time_s": [
            0.00010323524475097656,
            9.417533874511719e-05,
            0.0001399517059326172
          ],
          "obj_and_grad_eval_time_s": [
            0.0017206668853759766,
            0.0016837120056152344,
            0.0016977787017822266
          ],
          "predict_weight_time": [
            0.0,
            0.0,
            0.0
          ],
          "tf_time_s": [
            4.1484832763671875e-05,
            3.170967102050781e-05,
            3.528594970703125e-05
          ],
          "tot_obj_time_s": [
            0.03574228286743164,
            0.03479743003845215,
            0.02808856964111328
          ]
        }
      },
      "lbfgs_iterations": 2,
      "mouse_info": {
        "dragged_mesh_pos": [
          0.0,
          0.0,
          0.0
        ],
        "dragged_pos": [
          0.0,
          0.0,
          0.0
        ],
        "is_dragging": false
      },
      "precondition_time": 0.5561232566833496,
      "tot_step_time_s": 0.6752874851226807
    },
    {
      "current_frame": 17,
      "iteration_info": {
        "lbfgs_iteration": [
          0,
          1,
          2
        ],
        "lbfgs_line_iteration": [
          0,
          0,
          0
        ],
        "lbfgs_obj_vals": [
          6.292801383129048e-07,
          6.060305363836962e-07,
          6.060217456149638e-07
        ],
        "timing": {
          "energy_forces_time_s": [
            0.03798079490661621,
            0.03018951416015625,
            0.023856639862060547
          ],
          "linear_decode_time_s": [
            0.00011110305786132813,
            9.179115295410156e-05,
            0.00010275840759277344
          ],
          "obj_and_grad_eval_time_s": [
            0.0017158985137939453,
            0.0016644001007080078,
            0.0018885135650634766
          ],
          "predict_weight_time": [
            0.0,
            0.0,
            0.0
          ],
          "tf_time_s": [
            4.00543212890625e-05,
            3.218650817871094e-05,
            3.218650817871094e-05
          ],
          "tot_obj_time_s": [
            0.03985023498535156,
            0.031980037689208984,
            0.025882720947265625
          ]
        }
      },
      "lbfgs_iterations": 2,
      "mouse_info": {
        "dragged_mesh_pos": [
          0.0,
          0.0,
          0.0
        ],
        "dragged_pos": [
          0.0,
          0.0,
          0.0
        ],
        "is_dragging": false
      },
      "precondition_time": 0.5474729537963867,
      "tot_step_time_s": 0.6650614738464355
    },
    {
      "current_frame": 18,
      "iteration_info": {
        "lbfgs_iteration": [
          0,
          1,
          2
        ],
        "lbfgs_line_iteration": [
          0,
          0,
          0
        ],
        "lbfgs_obj_vals": [
          6.045134725666397e-07,
          5.621731629123544e-07,
          5.621492577472777e-07
        ],
        "timing": {
          "energy_forces_time_s": [
            0.0408475399017334,
            0.014326810836791992,
            0.01282048225402832
          ],
          "linear_decode_time_s": [
            8.511543273925781e-05,
            8.511543273925781e-05,
            8.344650268554688e-05
          ],
          "obj_and_grad_eval_time_s": [
            0.001659393310546875,
            0.001650094985961914,
            0.0016493797302246094
          ],
          "predict_weight_time": [
            0.0,
            0.0,
            0.0
          ],
          "tf_time_s": [
            4.601478576660156e-05,
            3.0279159545898438e-05,
            3.075599670410156e-05
          ],
          "tot_obj_time_s": [
            0.04264068603515625,
            0.016094684600830078,
            0.01458597183227539
          ]
        }
      },
      "lbfgs_iterations": 2,
      "mouse_info": {
        "dragged_mesh_pos": [
          0.0,
          0.0,
          0.0
        ],
        "dragged_pos": [
          0.0,
          0.0,
          0.0
        ],
        "is_dragging": false
      },
      "precondition_time": 0.4882049560546875,
      "tot_step_time_s": 0.5804977416992188
    },
    {
      "current_frame": 19,
      "iteration_info": {
        "lbfgs_iteration": [
          0,
          1,
          2
        ],
        "lbfgs_line_iteration": [
          0,
          0,
          0
        ],
        "lbfgs_obj_vals": [
          5.747736327428463e-07,
          5.143406982056604e-07,
          5.142975390170435e-07
        ],
        "timing": {
          "energy_forces_time_s": [
            0.05959010124206543,
            0.030847549438476563,
            0.015718936920166016
          ],
          "linear_decode_time_s": [
            8.845329284667969e-05,
            0.00010824203491210938,
            0.00011610984802246094
          ],
          "obj_and_grad_eval_time_s": [
            0.0016908645629882813,
            0.002505779266357422,
            0.0022101402282714844
          ],
          "predict_weight_time": [
            0.0,
            0.0,
            0.0
          ],
          "tf_time_s": [
            4.38690185546875e-05,
            3.6716461181640625e-05,
            3.552436828613281e-05
          ],
          "tot_obj_time_s": [
            0.06141519546508789,
            0.03350043296813965,
            0.018082857131958008
          ]
        }
      },
      "lbfgs_iterations": 2,
      "mouse_info": {
        "dragged_mesh_pos": [
          0.0,
          0.0,
          0.0
        ],
        "dragged_pos": [
          0.0,
          0.0,
          0.0
        ],
        "is_dragging": false
      },
      "precondition_time": 0.5482518672943115,
      "tot_step_time_s": 0.6822445392608643
    },
    {
      "current_frame": 20,
      "iteration_info": {
        "lbfgs_iteration": [
          0,
          1,
          2
        ],
        "lbfgs_line_iteration": [
          0,
          0,
          0
        ],
        "lbfgs_obj_vals": [
          5.389972672321521e-07,
          4.648905657966146e-07,
          4.64832928370263e-07
        ],
        "timing": {
          "energy_forces_time_s": [
            0.048356056213378906,
            0.029967784881591797,
            0.026094436645507813
          ],
          "linear_decode_time_s": [
            0.00022721290588378906,
            0.00012111663818359375,
            0.00011157989501953125
          ],
          "obj_and_grad_eval_time_s": [
            0.003130197525024414,
            0.0022895336151123047,
            0.0015642642974853516
          ],
          "predict_weight_time": [
            0.0,
            0.0,
            0.0
          ],
          "tf_time_s": [
            8.940696716308594e-05,
            3.7670135498046875e-05,
            3.528594970703125e-05
          ],
          "tot_obj_time_s": [
            0.05180549621582031,
            0.03241848945617676,
            0.02780747413635254
          ]
        }
      },
      "lbfgs_iterations": 2,
      "mouse_info": {
        "dragged_mesh_pos": [
          0.0,
          0.0,
          0.0
        ],
        "dragged_pos": [
          0.0,
          0.0,
          0.0
        ],
        "is_dragging": false
      },
      "precondition_time": 0.5413260459899902,
      "tot_step_time_s": 0.6750128269195557
    },
    {
      "current_frame": 21,
      "iteration_info": {
        "lbfgs_iteration": [
          0,
          1,
          2
        ],
        "lbfgs_line_iteration": [
          0,
          0,
          0
        ],
        "lbfgs_obj_vals": [
          4.968666306629266e-07,
          4.15207046043522e-07,
          4.1514641203959134e-07
        ],
        "timing": {
          "energy_forces_time_s": [
            0.03177905082702637,
            0.039353370666503906,
            0.030307292938232422
          ],
          "linear_decode_time_s": [
            0.00016546249389648438,
            0.00010085105895996094,
            0.00011014938354492188
          ],
          "obj_and_grad_eval_time_s": [
            0.0023200511932373047,
            0.002045154571533203,
            0.0026721954345703125
          ],
          "predict_weight_time": [
            0.0,
            0.0,
            0.0
          ],
          "tf_time_s": [
            5.7220458984375e-05,
            3.6716461181640625e-05,
            3.719329833984375e-05
          ],
          "tot_obj_time_s": [
            0.03432416915893555,
            0.04153871536254883,
            0.03312945365905762
          ]
        }
      },
      "lbfgs_iterations": 2,
      "mouse_info": {
        "dragged_mesh_pos": [
          0.0,
          0.0,
          0.0
        ],
        "dragged_pos": [
          0.0,
          0.0,
          0.0
        ],
        "is_dragging": false
      },
      "precondition_time": 0.5341842174530029,
      "tot_step_time_s": 0.6676294803619385
    }
  ]
}