{
  "sim_config": {
    "integrator_config": {
      "ae_decoded_dim": 35,
      "ae_encoded_dim": 20,
      "finite_diff_eps": 5e-05,
      "gravity": -9.8,
      "lbfgs_config": {
        "lbfgs_epsilon": 0.0001,
        "lbfgs_m": 10,
        "lbfgs_max_iterations": 150
      },
      "pca_dim": 35,
      "reduced_energy_method": "pcr",
      "reduced_space_type": "autoencoder",
      "timestep": 0.03,
      "use_analytic_jac": true,
      "use_preconditioner": true,
      "use_reduced_energy": true
    },
    "logging_enabled": true,
    "material_config": {
      "density": 100.0,
      "poissons_ratio": 0.45,
      "youngs_modulus": 1000000.0
    },
    "mesh": "models/30k-armadillo-waist/tets.mesh",
    "visualization_config": {
      "full_space_constrained_axis": 1,
      "interaction_spring_stiffness": 100000.0,
      "show_stress": false
    }
  },
  "timesteps": [
    {
      "avg_activated_tets": null,
      "current_frame": 0,
      "iteration_info": {
        "lbfgs_obj_vals": [
          0.869839666543445,
          -0.491611429810275,
          -0.516132212801696,
          -0.517810504691006,
          -0.517828089465719,
          -0.517829915973963,
          -0.517829982988521,
          -0.517829986417424
        ],
        "timing": {
          "energy_forces_time_s": [
            0.00380635261535645,
            0.00097203254699707,
            0.00101041793823242,
            0.00103592872619629,
            0.00102901458740234,
            0.00131344795227051,
            0.00157785415649414,
            0.00113725662231445
          ],
          "linear_decode_time_s": [
            0.00853347778320312,
            0.00726842880249023,
            0.0150914192199707,
            0.00729656219482422,
            0.00658154487609863,
            0.00887322425842285,
            0.019519567489624,
            0.00928139686584473
          ],
          "obj_and_grad_eval_time_s": [
            0.00393915176391602,
            0.00011754035949707,
            0.00011754035949707,
            8.58306884765625e-05,
            8.29696655273438e-05,
            0.000164985656738281,
            0.000196456909179688,
            0.00016331672668457
          ],
          "predict_weight_time": [
            0.0,
            0.0,
            0.0,
            0.0,
            0.0,
            0.0,
            0.0,
            0.0
          ],
          "tf_time_s": [
            6.65187835693359e-05,
            7.93933868408203e-05,
            6.29425048828125e-05,
            6.69956207275391e-05,
            4.64916229248047e-05,
            4.57763671875e-05,
            7.77244567871094e-05,
            8.79764556884766e-05
          ],
          "tot_obj_time_s": [
            0.0163521766662598,
            0.00844073295593262,
            0.0162856578826904,
            0.00849056243896484,
            0.00774455070495605,
            0.0104005336761475,
            0.021376371383667,
            0.0106732845306396
          ]
        }
      },
      "lbfgs_iterations": 7,
      "mouse_info": {
        "dragged_pos": [
          0.0,
          0.0,
          0.0
        ],
        "is_dragging": false
      },
      "precondition_time": 0.00139260292053223,
      "tot_step_time_s": 0.101593971252441
    },
    {
      "avg_activated_tets": 59900.0,
      "current_frame": 1,
      "iteration_info": {
        "lbfgs_obj_vals": [
          2.93477283311099,
          0.134308470213196,
          0.107338542908066,
          0.104130822800237,
          0.104015888052683,
          0.104005213431352,
          0.104004685693996,
          0.104004634741821,
          0.104004630749107
        ],
        "timing": {
          "energy_forces_time_s": [
            0.00129008293151855,
            0.00110507011413574,
            0.00106573104858398,
            0.00107264518737793,
            0.00111246109008789,
            0.00166940689086914,
            0.000898361206054688,
            0.000840187072753906,
            0.00105047225952148
          ],
          "linear_decode_time_s": [
            0.00642728805541992,
            0.0057835578918457,
            0.00964665412902832,
            0.00940871238708496,
            0.00735116004943848,
            0.00594425201416016,
            0.00552892684936523,
            0.00508594512939453,
            0.0181753635406494
          ],
          "obj_and_grad_eval_time_s": [
            0.000110864639282227,
            0.000113010406494141,
            0.000114202499389648,
            0.000123023986816406,
            0.000128269195556641,
            0.000129938125610352,
            0.000101327896118164,
            0.000113010406494141,
            0.000123739242553711
          ],
          "predict_weight_time": [
            0.0,
            0.0,
            0.0,
            0.0,
            0.0,
            0.0,
            0.0,
            0.0,
            0.0
          ],
          "tf_time_s": [
            4.52995300292969e-05,
            4.86373901367188e-05,
            6.69956207275391e-05,
            4.9591064453125e-05,
            5.26905059814453e-05,
            6.05583190917969e-05,
            5.17368316650391e-05,
            6.36577606201172e-05,
            5.12599945068359e-05
          ],
          "tot_obj_time_s": [
            0.00787687301635742,
            0.00705289840698242,
            0.0108964443206787,
            0.0106585025787354,
            0.00864815711975098,
            0.00780749320983887,
            0.00658321380615234,
            0.00610566139221191,
            0.0194036960601807
          ]
        }
      },
      "lbfgs_iterations": 8,
      "mouse_info": {
        "dragged_pos": [
          0.0,
          0.0,
          0.0
        ],
        "is_dragging": false
      },
      "precondition_time": 0.0011599063873291,
      "tot_step_time_s": 0.0864758491516113
    },
    {
      "avg_activated_tets": 44925.0,
      "current_frame": 2,
      "iteration_info": {
        "lbfgs_obj_vals": [
          6.01229358101719,
          1.63662056891998,
          1.59342975654551,
          1.58699975695239,
          1.58672090384582,
          1.58670762253353,
          1.58670688869916,
          1.5867068265516
        ],
        "timing": {
          "energy_forces_time_s": [
            0.00114107131958008,
            0.000867605209350586,
            0.00108647346496582,
            0.000856637954711914,
            0.000844240188598633,
            0.000821590423583984,
            0.000839471817016602,
            0.000810384750366211
          ],
          "linear_decode_time_s": [
            0.00686812400817871,
            0.00531768798828125,
            0.00994038581848145,
            0.00497674942016602,
            0.00484824180603027,
            0.00486016273498535,
            0.0048375129699707,
            0.00455808639526367
          ],
          "obj_and_grad_eval_time_s": [
            0.000109672546386719,
            0.000111103057861328,
            0.000130653381347656,
            0.000107288360595703,
            8.84532928466797e-05,
            9.08374786376953e-05,
            0.000113725662231445,
            0.000121355056762695
          ],
          "predict_weight_time": [
            0.0,
            0.0,
            0.0,
            0.0,
            0.0,
            0.0,
            0.0,
            0.0
          ],
          "tf_time_s": [
            6.58035278320312e-05,
            6.91413879394531e-05,
            9.13143157958984e-05,
            5.96046447753906e-05,
            5.88893890380859e-05,
            5.43594360351562e-05,
            5.38825988769531e-05,
            5.45978546142578e-05
          ],
          "tot_obj_time_s": [
            0.00818729400634766,
            0.00636935234069824,
            0.0112514495849609,
            0.00600600242614746,
            0.0058436393737793,
            0.00583148002624512,
            0.00584697723388672,
            0.00554776191711426
          ]
        }
      },
      "lbfgs_iterations": 7,
      "mouse_info": {
        "dragged_pos": [
          0.0,
          0.0,
          0.0
        ],
        "is_dragging": false
      },
      "precondition_time": 0.00121784210205078,
      "tot_step_time_s": 0.0563104152679443
    },
    {
      "avg_activated_tets": 39933.3333333333,
      "current_frame": 3,
      "iteration_info": {
        "lbfgs_obj_vals": [
          9.60071989556303,
          3.61034575289735,
          3.5527756018348,
          3.54461851239786,
          3.54408898366521,
          3.54406215392408,
          3.544061008703,
          3.5440609433737
        ],
        "timing": {
          "energy_forces_time_s": [
            0.00145697593688965,
            0.00128412246704102,
            0.00122475624084473,
            0.00112605094909668,
            0.000878572463989258,
            0.0010077953338623,
            0.000829696655273438,
            0.000890731811523438
          ],
          "linear_decode_time_s": [
            0.0104837417602539,
            0.00865936279296875,
            0.0084693431854248,
            0.0122935771942139,
            0.00775265693664551,
            0.00687432289123535,
            0.00736427307128906,
            0.0157322883605957
          ],
          "obj_and_grad_eval_time_s": [
            0.000124216079711914,
            0.000116348266601562,
            0.000123262405395508,
            0.000121355056762695,
            9.48905944824219e-05,
            9.82284545898438e-05,
            8.96453857421875e-05,
            0.00010228157043457
          ],
          "predict_weight_time": [
            0.0,
            0.0,
            0.0,
            0.0,
            0.0,
            0.0,
            0.0,
            0.0
          ],
          "tf_time_s": [
            6.65187835693359e-05,
            6.46114349365234e-05,
            6.4849853515625e-05,
            7.41481781005859e-05,
            6.41345977783203e-05,
            5.36441802978516e-05,
            7.82012939453125e-05,
            5.45978546142578e-05
          ],
          "tot_obj_time_s": [
            0.0121340751647949,
            0.0101275444030762,
            0.00988507270812988,
            0.0136184692382812,
            0.00879335403442383,
            0.00803661346435547,
            0.00836396217346191,
            0.0167825222015381
          ]
        }
      },
      "lbfgs_iterations": 7,
      "mouse_info": {
        "dragged_pos": [
          0.0,
          0.0,
          0.0
        ],
        "is_dragging": false
      },
      "precondition_time": 0.00140571594238281,
      "tot_step_time_s": 0.0894167423248291
    },
    {
      "avg_activated_tets": 37437.5,
      "current_frame": 4,
      "iteration_info": {
        "lbfgs_obj_vals": [
          13.3639522121791,
          5.85527162856877,
          5.79001277664755,
          5.78046456393324,
          5.77916320348405,
          5.77912354212465,
          5.77911966729165,
          5.77911938525806
        ],
        "timing": {
          "energy_forces_time_s": [
            0.00135183334350586,
            0.000897407531738281,
            0.00102853775024414,
            0.00084233283996582,
            0.000829696655273438,
            0.00139665603637695,
            0.00130224227905273,
            0.00118088722229004
          ],
          "linear_decode_time_s": [
            0.00865721702575684,
            0.00652670860290527,
            0.0102152824401855,
            0.00683212280273438,
            0.00635981559753418,
            0.00980329513549805,
            0.0160286426544189,
            0.00945520401000977
          ],
          "obj_and_grad_eval_time_s": [
            0.000156164169311523,
            0.000123023986816406,
            0.000139236450195312,
            0.00011444091796875,
            0.000133991241455078,
            0.00015711784362793,
            0.000159502029418945,
            0.000144243240356445
          ],
          "predict_weight_time": [
            0.0,
            0.0,
            0.0,
            0.0,
            0.0,
            0.0,
            0.0,
            0.0
          ],
          "tf_time_s": [
            6.31809234619141e-05,
            6.43730163574219e-05,
            7.86781311035156e-05,
            7.55786895751953e-05,
            6.65187835693359e-05,
            6.00814819335938e-05,
            7.72476196289062e-05,
            7.46250152587891e-05
          ],
          "tot_obj_time_s": [
            0.01023268699646,
            0.0076148509979248,
            0.0114645957946777,
            0.00786685943603516,
            0.00739288330078125,
            0.0114200115203857,
            0.0175704956054688,
            0.0108578205108643
          ]
        }
      },
      "lbfgs_iterations": 7,
      "mouse_info": {
        "dragged_pos": [
          0.0,
          0.0,
          0.0
        ],
        "is_dragging": false
      },
      "precondition_time": 0.00135135650634766,
      "tot_step_time_s": 0.0861046314239502
    },
    {
      "avg_activated_tets": 35940.0,
      "current_frame": 5,
      "iteration_info": {
        "lbfgs_obj_vals": [
          16.9386135476185,
          8.26544250042388,
          8.21076671096012,
          8.2010230807515,
          8.19925370167773,
          8.19917115410229,
          8.19916219915122,
          8.19916151709227
        ],
        "timing": {
          "energy_forces_time_s": [
            0.00170636177062988,
            0.00169682502746582,
            0.00120115280151367,
            0.00108957290649414,
            0.00102472305297852,
            0.000959634780883789,
            0.000987052917480469,
            0.000979185104370117
          ],
          "linear_decode_time_s": [
            0.0125555992126465,
            0.0124821662902832,
            0.00925683975219727,
            0.0066826343536377,
            0.0068509578704834,
            0.00642681121826172,
            0.0196764469146729,
            0.00629520416259766
          ],
          "obj_and_grad_eval_time_s": [
            0.000153541564941406,
            0.000174283981323242,
            0.000116825103759766,
            0.000128269195556641,
            0.000111579895019531,
            9.34600830078125e-05,
            0.00012660026550293,
            0.000156641006469727
          ],
          "predict_weight_time": [
            0.0,
            0.0,
            0.0,
            0.0,
            0.0,
            0.0,
            0.0,
            0.0
          ],
          "tf_time_s": [
            7.46250152587891e-05,
            7.22408294677734e-05,
            7.65323638916016e-05,
            6.19888305664062e-05,
            5.69820404052734e-05,
            5.84125518798828e-05,
            6.07967376708984e-05,
            6.15119934082031e-05
          ],
          "tot_obj_time_s": [
            0.0144937038421631,
            0.0144279003143311,
            0.0106544494628906,
            0.00796747207641602,
            0.00804686546325684,
            0.00754189491271973,
            0.0208570957183838,
            0.00749611854553223
          ]
        }
      },
      "lbfgs_iterations": 7,
      "mouse_info": {
        "dragged_pos": [
          0.0,
          0.0,
          0.0
        ],
        "is_dragging": false
      },
      "precondition_time": 0.00148797035217285,
      "tot_step_time_s": 0.0932610034942627
    },
    {
      "avg_activated_tets": 34941.6666666667,
      "current_frame": 6,
      "iteration_info": {
        "lbfgs_obj_vals": [
          20.0530873182393,
          10.5235937225863,
          10.4496657108383,
          10.436576296007,
          10.434208048825,
          10.4340253595741,
          10.4340085906796,
          10.4340073499749
        ],
        "timing": {
          "energy_forces_time_s": [
            0.0012969970703125,
            0.00100970268249512,
            0.000901699066162109,
            0.000895500183105469,
            0.00095677375793457,
            0.000872611999511719,
            0.000854730606079102,
            0.000940322875976562
          ],
          "linear_decode_time_s": [
            0.00704407691955566,
            0.00737261772155762,
            0.00553297996520996,
            0.00539994239807129,
            0.00507235527038574,
            0.00513172149658203,
            0.0045320987701416,
            0.0175886154174805
          ],
          "obj_and_grad_eval_time_s": [
            0.000137805938720703,
            0.000138998031616211,
            0.000160932540893555,
            0.000124454498291016,
            0.000164508819580078,
            0.000152349472045898,
            0.000166177749633789,
            0.00014042854309082
          ],
          "predict_weight_time": [
            0.0,
            0.0,
            0.0,
            0.0,
            0.0,
            0.0,
            0.0,
            0.0
          ],
          "tf_time_s": [
            7.03334808349609e-05,
            8.58306884765625e-05,
            6.84261322021484e-05,
            6.84261322021484e-05,
            6.74724578857422e-05,
            6.93798065185547e-05,
            8.17775726318359e-05,
            8.74996185302734e-05
          ],
          "tot_obj_time_s": [
            0.00855183601379395,
            0.00860977172851562,
            0.00666713714599609,
            0.00649142265319824,
            0.00626444816589355,
            0.00622940063476562,
            0.00563955307006836,
            0.0187594890594482
          ]
        }
      },
      "lbfgs_iterations": 7,
      "mouse_info": {
        "dragged_pos": [
          0.0,
          0.0,
          0.0
        ],
        "is_dragging": false
      },
      "precondition_time": 0.00142788887023926,
      "tot_step_time_s": 0.0688810348510742
    },
    {
      "avg_activated_tets": 34228.5714285714,
      "current_frame": 7,
      "iteration_info": {
        "lbfgs_obj_vals": [
          22.7398866699716,
          12.0531242522352,
          11.8904967059665,
          11.8436041029692,
          11.8345652398524,
          11.8335054740273,
          11.8334081649715,
          11.8333994683627,
          11.8333991998723
        ],
        "timing": {
          "energy_forces_time_s": [
            0.00121140480041504,
            0.0008392333984375,
            0.000830411911010742,
            0.000943183898925781,
            0.000830411911010742,
            0.000816583633422852,
            0.000820636749267578,
            0.000815629959106445,
            0.00102043151855469
          ],
          "linear_decode_time_s": [
            0.00700044631958008,
            0.00559616088867188,
            0.00474381446838379,
            0.0125179290771484,
            0.00520634651184082,
            0.00514531135559082,
            0.00503444671630859,
            0.0050208568572998,
            0.0192859172821045
          ],
          "obj_and_grad_eval_time_s": [
            0.000158786773681641,
            0.000130653381347656,
            0.000128507614135742,
            0.000148773193359375,
            0.000131845474243164,
            0.000128269195556641,
            0.000128746032714844,
            0.000153303146362305,
            0.000184059143066406
          ],
          "predict_weight_time": [
            0.0,
            0.0,
            0.0,
            0.0,
            0.0,
            0.0,
            0.0,
            0.0,
            0.0
          ],
          "tf_time_s": [
            7.46250152587891e-05,
            7.93933868408203e-05,
            9.82284545898438e-05,
            6.62803649902344e-05,
            6.84261322021484e-05,
            6.60419464111328e-05,
            6.34193420410156e-05,
            6.34193420410156e-05,
            6.19888305664062e-05
          ],
          "tot_obj_time_s": [
            0.00844860076904297,
            0.00664806365966797,
            0.00580406188964844,
            0.0136797428131104,
            0.00623941421508789,
            0.00615882873535156,
            0.00604939460754395,
            0.00605607032775879,
            0.0205557346343994
          ]
        }
      },
      "lbfgs_iterations": 8,
      "mouse_info": {
        "dragged_pos": [
          0.0,
          0.0,
          0.0
        ],
        "is_dragging": false
      },
      "precondition_time": 0.00150680541992188,
      "tot_step_time_s": 0.0814235210418701
    },
    {
      "avg_activated_tets": 33693.75,
      "current_frame": 8,
      "iteration_info": {
        "lbfgs_obj_vals": [
          25.5642346309832,
          12.4048888652251,
          12.1236248133378,
          12.0341900855081,
          12.0207149868558,
          12.0197137705574,
          12.019669924067,
          12.019666440036,
          12.0196660261253
        ],
        "timing": {
          "energy_forces_time_s": [
            0.00103998184204102,
            0.000762224197387695,
            0.000941038131713867,
            0.000753402709960938,
            0.000752449035644531,
            0.000717401504516602,
            0.000716686248779297,
            0.00337934494018555,
            0.00126171112060547
          ],
          "linear_decode_time_s": [
            0.00681233406066895,
            0.0054786205291748,
            0.00895309448242188,
            0.00512003898620605,
            0.00503182411193848,
            0.00494885444641113,
            0.00499057769775391,
            0.00491476058959961,
            0.0217418670654297
          ],
          "obj_and_grad_eval_time_s": [
            0.000179767608642578,
            0.000123977661132812,
            0.000105142593383789,
            0.000117301940917969,
            0.00012969970703125,
            0.000131368637084961,
            0.000125408172607422,
            0.000227928161621094,
            0.000181198120117188
          ],
          "predict_weight_time": [
            0.0,
            0.0,
            0.0,
            0.0,
            0.0,
            0.0,
            0.0,
            0.0,
            0.0
          ],
          "tf_time_s": [
            6.55651092529297e-05,
            6.91413879394531e-05,
            6.27040863037109e-05,
            5.57899475097656e-05,
            5.98430633544922e-05,
            6.15119934082031e-05,
            6.22272491455078e-05,
            6.07967376708984e-05,
            0.000104665756225586
          ],
          "tot_obj_time_s": [
            0.00810027122497559,
            0.00643754005432129,
            0.0100662708282471,
            0.00604915618896484,
            0.00597739219665527,
            0.00586271286010742,
            0.00589752197265625,
            0.00858616828918457,
            0.0232937335968018
          ]
        }
      },
      "lbfgs_iterations": 8,
      "mouse_info": {
        "dragged_pos": [
          0.0,
          0.0,
          0.0
        ],
        "is_dragging": false
      },
      "precondition_time": 0.00147032737731934,
      "tot_step_time_s": 0.0820894241333008
    },
    {
      "avg_activated_tets": 33277.7777777778,
      "current_frame": 9,
      "iteration_info": {
        "lbfgs_obj_vals": [
          28.9025939339573,
          13.1739940386637,
          12.8416891053218,
          12.7436605834608,
          12.7301430282533,
          12.7292941470196,
          12.7292423368592,
          12.7292406522106
        ],
        "timing": {
          "energy_forces_time_s": [
            0.000931024551391602,
            0.000721216201782227,
            0.000771522521972656,
            0.000822305679321289,
            0.000767946243286133,
            0.000724315643310547,
            0.000746726989746094,
            0.000737428665161133
          ],
          "linear_decode_time_s": [
            0.00701999664306641,
            0.0055239200592041,
            0.00539135932922363,
            0.0167226791381836,
            0.00516033172607422,
            0.00517916679382324,
            0.00509786605834961,
            0.00514793395996094
          ],
          "obj_and_grad_eval_time_s": [
            0.000138998031616211,
            0.000129938125610352,
            0.000116825103759766,
            0.000113487243652344,
            0.000128030776977539,
            9.84668731689453e-05,
            0.000101566314697266,
            0.000102043151855469
          ],
          "predict_weight_time": [
            0.0,
            0.0,
            0.0,
            0.0,
            0.0,
            0.0,
            0.0,
            0.0
          ],
          "tf_time_s": [
            6.866455078125e-05,
            6.50882720947266e-05,
            6.31809234619141e-05,
            7.62939453125e-05,
            0.000111818313598633,
            6.19888305664062e-05,
            6.19888305664062e-05,
            6.4849853515625e-05
          ],
          "tot_obj_time_s": [
            0.00816178321838379,
            0.00644302368164062,
            0.00634622573852539,
            0.0177388191223145,
            0.00617027282714844,
            0.00606656074523926,
            0.0060114860534668,
            0.00605559349060059
          ]
        }
      },
      "lbfgs_iterations": 7,
      "mouse_info": {
        "dragged_pos": [
          0.0,
          0.0,
          0.0
        ],
        "is_dragging": false
      },
      "precondition_time": 0.00170540809631348,
      "tot_step_time_s": 0.06498122215271
    },
    {
      "avg_activated_tets": 32945.0,
      "current_frame": 10,
      "iteration_info": {
        "lbfgs_obj_vals": [
          32.5880247317718,
          15.1482006423506,
          14.7343001293266,
          14.6231600560077,
          14.607306599819,
          14.605214787406,
          14.6049982537551,
          14.6049814421765,
          14.6049784540422
        ],
        "timing": {
          "energy_forces_time_s": [
            0.000934600830078125,
            0.000726461410522461,
            0.00075531005859375,
            0.000836849212646484,
            0.000720739364624023,
            0.000741243362426758,
            0.000811576843261719,
            0.000823974609375,
            0.001068115234375
          ],
          "linear_decode_time_s": [
            0.00621247291564941,
            0.00542736053466797,
            0.00546479225158691,
            0.00499916076660156,
            0.0050044059753418,
            0.00470113754272461,
            0.0212454795837402,
            0.00505638122558594,
            0.00532650947570801
          ],
          "obj_and_grad_eval_time_s": [
            0.000130891799926758,
            0.000129938125610352,
            0.000153541564941406,
            0.000133514404296875,
            0.000149965286254883,
            0.000123739242553711,
            0.000144004821777344,
            0.000133991241455078,
            0.000123977661132812
          ],
          "predict_weight_time": [
            0.0,
            0.0,
            0.0,
            0.0,
            0.0,
            0.0,
            0.0,
            0.0,
            0.0
          ],
          "tf_time_s": [
            7.74860382080078e-05,
            7.82012939453125e-05,
            5.57899475097656e-05,
            7.72476196289062e-05,
            6.91413879394531e-05,
            7.74860382080078e-05,
            6.31809234619141e-05,
            6.93798065185547e-05,
            6.60419464111328e-05
          ],
          "tot_obj_time_s": [
            0.00735902786254883,
            0.00636482238769531,
            0.00643277168273926,
            0.00605130195617676,
            0.00594735145568848,
            0.0056464672088623,
            0.0222680568695068,
            0.00608611106872559,
            0.00658917427062988
          ]
        }
      },
      "lbfgs_iterations": 8,
      "mouse_info": {
        "dragged_pos": [
          0.0,
          0.0,
          0.0
        ],
        "is_dragging": false
      },
      "precondition_time": 0.0014183521270752,
      "tot_step_time_s": 0.0744147300720215
    },
    {
      "avg_activated_tets": 32672.7272727273,
      "current_frame": 11,
      "iteration_info": {
        "lbfgs_obj_vals": [
          36.3734302436724,
          17.6654345079324,
          17.0313859275159,
          16.847975232547,
          16.8112063962533,
          16.8072433828883,
          16.8062923891198,
          16.8061791097123,
          16.8061360465073,
          16.8061334007707
        ],
        "timing": {
          "energy_forces_time_s": [
            0.00116157531738281,
            0.000779151916503906,
            0.000820159912109375,
            0.000764131546020508,
            0.000759601593017578,
            0.000757455825805664,
            0.000766515731811523,
            0.000770092010498047,
            0.000757932662963867,
            0.000726222991943359
          ],
          "linear_decode_time_s": [
            0.00687670707702637,
            0.0112550258636475,
            0.0054628849029541,
            0.00550436973571777,
            0.00524544715881348,
            0.00520968437194824,
            0.0187766551971436,
            0.00526952743530273,
            0.00531148910522461,
            0.00516080856323242
          ],
          "obj_and_grad_eval_time_s": [
            0.000120162963867188,
            0.000103950500488281,
            0.000129938125610352,
            9.67979431152344e-05,
            9.75131988525391e-05,
            9.39369201660156e-05,
            0.000102043151855469,
            0.000101089477539062,
            9.41753387451172e-05,
            9.44137573242188e-05
          ],
          "predict_weight_time": [
            0.0,
            0.0,
            0.0,
            0.0,
            0.0,
            0.0,
            0.0,
            0.0,
            0.0,
            0.0
          ],
          "tf_time_s": [
            6.24656677246094e-05,
            7.48634338378906e-05,
            6.43730163574219e-05,
            6.03199005126953e-05,
            5.98430633544922e-05,
            6.00814819335938e-05,
            6.05583190917969e-05,
            5.96046447753906e-05,
            6.12735748291016e-05,
            5.96046447753906e-05
          ],
          "tot_obj_time_s": [
            0.0082244873046875,
            0.0122168064117432,
            0.00647974014282227,
            0.00642895698547363,
            0.00616574287414551,
            0.00612378120422363,
            0.019709587097168,
            0.00620460510253906,
            0.00622773170471191,
            0.00604605674743652
          ]
        }
      },
      "lbfgs_iterations": 9,
      "mouse_info": {
        "dragged_pos": [
          0.0,
          0.0,
          0.0
        ],
        "is_dragging": false
      },
      "precondition_time": 0.00144600868225098,
      "tot_step_time_s": 0.0855205059051514
    },
    {
      "avg_activated_tets": 32445.8333333333,
      "current_frame": 12,
      "iteration_info": {
        "lbfgs_obj_vals": [
          40.3927041496455,
          20.2082615462364,
          19.3141816194078,
          18.9626825973834,
          18.880100005895,
          18.8560117163115,
          18.8507091057512,
          18.8497858955602,
          18.8494621040052,
          18.8494306342158,
          18.8494283909184
        ],
        "timing": {
          "energy_forces_time_s": [
            0.000943422317504883,
            0.000799179077148438,
            0.000777721405029297,
            0.000955343246459961,
            0.000810623168945312,
            0.000756263732910156,
            0.000770330429077148,
            0.000762939453125,
            0.000795125961303711,
            0.00116991996765137,
            0.000977277755737305
          ],
          "linear_decode_time_s": [
            0.0067751407623291,
            0.00456380844116211,
            0.00496506690979004,
            0.00957202911376953,
            0.00506973266601562,
            0.00491547584533691,
            0.00494241714477539,
            0.0046846866607666,
            0.00479769706726074,
            0.0425317287445068,
            0.00537824630737305
          ],
          "obj_and_grad_eval_time_s": [
            0.000134706497192383,
            0.000114202499389648,
            0.000110387802124023,
            0.000113964080810547,
            0.000115871429443359,
            8.29696655273438e-05,
            8.65459442138672e-05,
            7.65323638916016e-05,
            0.000118732452392578,
            0.000144481658935547,
            0.000152111053466797
          ],
          "predict_weight_time": [
            0.0,
            0.0,
            0.0,
            0.0,
            0.0,
            0.0,
            0.0,
            0.0,
            0.0,
            0.0,
            0.0
          ],
          "tf_time_s": [
            7.46250152587891e-05,
            6.12735748291016e-05,
            6.03199005126953e-05,
            5.14984130859375e-05,
            5.41210174560547e-05,
            5.10215759277344e-05,
            5.41210174560547e-05,
            5.31673431396484e-05,
            5.7220458984375e-05,
            5.36441802978516e-05,
            6.15119934082031e-05
          ],
          "tot_obj_time_s": [
            0.00792980194091797,
            0.00554156303405762,
            0.00591659545898438,
            0.0106956958770752,
            0.00605320930480957,
            0.00580787658691406,
            0.00585627555847168,
            0.00557994842529297,
            0.00577163696289062,
            0.0439021587371826,
            0.00657200813293457
          ]
        }
      },
      "lbfgs_iterations": 10,
      "mouse_info": {
        "dragged_pos": [
          0.0,
          0.0,
          0.0
        ],
        "is_dragging": false
      },
      "precondition_time": 0.0014805793762207,
      "tot_step_time_s": 0.111380100250244
    },
    {
      "avg_activated_tets": 32253.8461538462,
      "current_frame": 13,
      "iteration_info": {
        "lbfgs_obj_vals": [
          44.7243694175176,
          22.8749839900765,
          21.906413122016,
          21.1501906322457,
          20.9822542275812,
          20.8851112816955,
          20.8727511773916,
          20.8709721595865,
          20.8702123937458,
          20.8701326810288,
          20.8701265045887
        ],
        "timing": {
          "energy_forces_time_s": [
            0.00163984298706055,
            0.00136566162109375,
            0.00134682655334473,
            0.00124096870422363,
            0.00116467475891113,
            0.00109362602233887,
            0.00111079216003418,
            0.000994443893432617,
            0.00100827217102051,
            0.000993013381958008,
            0.0011751651763916
          ],
          "linear_decode_time_s": [
            0.0130796432495117,
            0.0111472606658936,
            0.00862002372741699,
            0.00892210006713867,
            0.00817465782165527,
            0.0073704719543457,
            0.0133867263793945,
            0.00745916366577148,
            0.00686383247375488,
            0.00647544860839844,
            0.022749662399292
          ],
          "obj_and_grad_eval_time_s": [
            0.000191450119018555,
            0.000137567520141602,
            0.000133752822875977,
            0.00013279914855957,
            0.000118732452392578,
            0.000119686126708984,
            0.000136852264404297,
            0.000117063522338867,
            0.000120401382446289,
            0.000113964080810547,
            0.000131845474243164
          ],
          "predict_weight_time": [
            0.0,
            0.0,
            0.0,
            0.0,
            0.0,
            0.0,
            0.0,
            0.0,
            0.0,
            0.0,
            0.0
          ],
          "tf_time_s": [
            7.15255737304688e-05,
            8.10623168945312e-05,
            6.72340393066406e-05,
            6.15119934082031e-05,
            6.81877136230469e-05,
            5.96046447753906e-05,
            6.29425048828125e-05,
            6.62803649902344e-05,
            5.41210174560547e-05,
            5.88893890380859e-05,
            6.53266906738281e-05
          ],
          "tot_obj_time_s": [
            0.0149850845336914,
            0.0127353668212891,
            0.0101702213287354,
            0.010359525680542,
            0.00952982902526855,
            0.00864577293395996,
            0.0146996974945068,
            0.00864028930664062,
            0.00805115699768066,
            0.0076441764831543,
            0.0241241455078125
          ]
        }
      },
      "lbfgs_iterations": 10,
      "mouse_info": {
        "dragged_pos": [
          0.0,
          0.0,
          0.0
        ],
        "is_dragging": false
      },
      "precondition_time": 0.00162696838378906,
      "tot_step_time_s": 0.131560325622559
    },
    {
      "avg_activated_tets": 32089.2857142857,
      "current_frame": 14,
      "iteration_info": {
        "lbfgs_obj_vals": [
          49.3424456657709,
          26.0574110348871,
          25.624559911779,
          23.7490632503733,
          23.4653706404894,
          23.2748873281546,
          23.2183865078632,
          23.2149448897121,
          23.2127793511726,
          23.2125451877107,
          23.2125185482334
        ],
        "timing": {
          "energy_forces_time_s": [
            0.00174045562744141,
            0.00109553337097168,
            0.0011296272277832,
            0.00105571746826172,
            0.0010218620300293,
            0.000990152359008789,
            0.000964879989624023,
            0.00160384178161621,
            0.00121450424194336,
            0.00106620788574219,
            0.000959873199462891
          ],
          "linear_decode_time_s": [
            0.00984287261962891,
            0.01346755027771,
            0.005706787109375,
            0.0131766796112061,
            0.00612354278564453,
            0.00605940818786621,
            0.00592517852783203,
            0.0447361469268799,
            0.0107855796813965,
            0.0159225463867188,
            0.00876045227050781
          ],
          "obj_and_grad_eval_time_s": [
            0.000183820724487305,
            0.00015711784362793,
            0.000131368637084961,
            0.000160455703735352,
            0.0001373291015625,
            0.000136852264404297,
            0.000136375427246094,
            0.000194311141967773,
            0.000180482864379883,
            0.000160455703735352,
            0.000135898590087891
          ],
          "predict_weight_time": [
            0.0,
            0.0,
            0.0,
            0.0,
            0.0,
            0.0,
            0.0,
            0.0,
            0.0,
            0.0,
            0.0
          ],
          "tf_time_s": [
            0.000111579895019531,
            8.32080841064453e-05,
            8.0108642578125e-05,
            7.31945037841797e-05,
            7.43865966796875e-05,
            8.10623168945312e-05,
            6.27040863037109e-05,
            7.79628753662109e-05,
            9.44137573242188e-05,
            6.84261322021484e-05,
            0.000102519989013672
          ],
          "tot_obj_time_s": [
            0.0118818283081055,
            0.0148065090179443,
            0.00705051422119141,
            0.0144684314727783,
            0.00736021995544434,
            0.00727081298828125,
            0.00709152221679688,
            0.0466146469116211,
            0.0122783184051514,
            0.0172204971313477,
            0.00996208190917969
          ]
        }
      },
      "lbfgs_iterations": 10,
      "mouse_info": {
        "dragged_pos": [
          0.0,
          0.0,
          0.0
        ],
        "is_dragging": false
      },
      "precondition_time": 0.00193285942077637,
      "tot_step_time_s": 0.158353805541992
    },
    {
      "avg_activated_tets": 31946.6666666667,
      "current_frame": 15,
      "iteration_info": {
        "lbfgs_obj_vals": [
          54.2861179833032,
          30.0588895001895,
          31.3508336582855,
          27.919225448036,
          27.0975192508919,
          26.515393707388,
          26.3222759013845,
          26.2867041126544,
          26.2812647718709,
          26.2784468588473,
          26.2778858610155,
          26.2778203900295,
          26.2778174291667
        ],
        "timing": {
          "energy_forces_time_s": [
            0.00135374069213867,
            0.00101971626281738,
            0.000961780548095703,
            0.000916957855224609,
            0.000890016555786133,
            0.000891447067260742,
            0.00105381011962891,
            0.00102138519287109,
            0.000982999801635742,
            0.000927209854125977,
            0.00114107131958008,
            0.00138068199157715,
            0.00143718719482422
          ],
          "linear_decode_time_s": [
            0.00732970237731934,
            0.00575017929077148,
            0.00538730621337891,
            0.00502467155456543,
            0.00485491752624512,
            0.00482797622680664,
            0.0236046314239502,
            0.00505733489990234,
            0.00474953651428223,
            0.00482797622680664,
            0.00906634330749512,
            0.040081262588501,
            0.0102744102478027
          ],
          "obj_and_grad_eval_time_s": [
            0.000173330307006836,
            0.000156641006469727,
            0.000102758407592773,
            9.48905944824219e-05,
            9.41753387451172e-05,
            9.44137573242188e-05,
            0.000133037567138672,
            9.51290130615234e-05,
            0.00010991096496582,
            9.63211059570312e-05,
            0.000194787979125977,
            0.000156879425048828,
            0.00017547607421875
          ],
          "predict_weight_time": [
            0.0,
            0.0,
            0.0,
            0.0,
            0.0,
            0.0,
            0.0,
            0.0,
            0.0,
            0.0,
            0.0,
            0.0,
            0.0
          ],
          "tf_time_s": [
            6.17504119873047e-05,
            8.32080841064453e-05,
            6.65187835693359e-05,
            7.17639923095703e-05,
            6.79492950439453e-05,
            5.48362731933594e-05,
            8.7738037109375e-05,
            5.86509704589844e-05,
            6.62803649902344e-05,
            6.17504119873047e-05,
            6.15119934082031e-05,
            0.000123262405395508,
            8.34465026855469e-05
          ],
          "tot_obj_time_s": [
            0.00892114639282227,
            0.00701427459716797,
            0.00652122497558594,
            0.00611138343811035,
            0.00591135025024414,
            0.00587177276611328,
            0.0248816013336182,
            0.00623631477355957,
            0.00591278076171875,
            0.00591754913330078,
            0.0104672908782959,
            0.0417447090148926,
            0.0119760036468506
          ]
        }
      },
      "lbfgs_iterations": 11,
      "mouse_info": {
        "dragged_pos": [
          0.0,
          0.0,
          0.0
        ],
        "is_dragging": false
      },
      "precondition_time": 0.00153732299804688,
      "tot_step_time_s": 0.149381875991821
    },
    {
      "avg_activated_tets": 31821.875,
      "current_frame": 16,
      "iteration_info": {
        "lbfgs_obj_vals": [
          59.4908306443844,
          34.5250926107971,
          39.2135409957647,
          32.4587265300803,
          31.3539499211644,
          30.5913637531584,
          30.2738336053503,
          30.1266333607395,
          30.1160752741571,
          30.1103036632876,
          30.1083413364931,
          30.1080125721267,
          30.1079931403594
        ],
        "timing": {
          "energy_forces_time_s": [
            0.00145244598388672,
            0.00115656852722168,
            0.00119924545288086,
            0.00112032890319824,
            0.0011744499206543,
            0.00118398666381836,
            0.00115036964416504,
            0.00105047225952148,
            0.00115561485290527,
            0.00107932090759277,
            0.00104308128356934,
            0.000991582870483398,
            0.00098729133605957
          ],
          "linear_decode_time_s": [
            0.00910735130310059,
            0.0107541084289551,
            0.00662803649902344,
            0.0123040676116943,
            0.00619816780090332,
            0.0057218074798584,
            0.0057837963104248,
            0.00508499145507812,
            0.0256216526031494,
            0.00612545013427734,
            0.00560092926025391,
            0.00545620918273926,
            0.00501894950866699
          ],
          "obj_and_grad_eval_time_s": [
            0.000175237655639648,
            0.00018310546875,
            0.000156164169311523,
            0.000176429748535156,
            0.000124216079711914,
            0.000104427337646484,
            0.000109195709228516,
            0.000152587890625,
            0.000138998031616211,
            0.000128984451293945,
            0.00014805793762207,
            0.000104904174804688,
            0.000120878219604492
          ],
          "predict_weight_time": [
            0.0,
            0.0,
            0.0,
            0.0,
            0.0,
            0.0,
            0.0,
            0.0,
            0.0,
            0.0,
            0.0,
            0.0,
            0.0
          ],
          "tf_time_s": [
            8.34465026855469e-05,
            7.03334808349609e-05,
            7.31945037841797e-05,
            7.48634338378906e-05,
            6.67572021484375e-05,
            6.77108764648438e-05,
            6.81877136230469e-05,
            6.41345977783203e-05,
            7.08103179931641e-05,
            6.53266906738281e-05,
            6.31809234619141e-05,
            8.89301300048828e-05,
            6.69956207275391e-05
          ],
          "tot_obj_time_s": [
            0.0108222961425781,
            0.0121676921844482,
            0.00805926322937012,
            0.0136787891387939,
            0.00756716728210449,
            0.00708198547363281,
            0.00711536407470703,
            0.00635457038879395,
            0.0269896984100342,
            0.00740265846252441,
            0.00685858726501465,
            0.00664448738098145,
            0.00619721412658691
          ]
        }
      },
      "lbfgs_iterations": 11,
      "mouse_info": {
        "dragged_pos": [
          0.0,
          0.0,
          0.0
        ],
        "is_dragging": false
      },
      "precondition_time": 0.00182151794433594,
      "tot_step_time_s": 0.129051685333252
    },
    {
      "avg_activated_tets": 31711.7647058824,
      "current_frame": 17,
      "iteration_info": {
        "lbfgs_obj_vals": [
          64.8023985680965,
          39.224705580917,
          46.1075023391816,
          37.4325645548931,
          36.2699384301752,
          35.3019853540411,
          34.8115586297156,
          34.59245498305,
          34.5101102961188,
          34.5028838636042,
          34.4976950609994,
          34.496059848357,
          34.4958279546777,
          34.4958176498974
        ],
        "timing": {
          "energy_forces_time_s": [
            0.00141358375549316,
            0.000931501388549805,
            0.00084233283996582,
            0.000909805297851562,
            0.000828981399536133,
            0.000870466232299805,
            0.000884056091308594,
            0.000806808471679688,
            0.000818490982055664,
            0.000808477401733398,
            0.000804901123046875,
            0.000912904739379883,
            0.000800132751464844,
            0.000825881958007812
          ],
          "linear_decode_time_s": [
            0.0123434066772461,
            0.00562763214111328,
            0.00562047958374023,
            0.00525593757629395,
            0.00511288642883301,
            0.0176384449005127,
            0.00534462928771973,
            0.00520873069763184,
            0.00491642951965332,
            0.00483298301696777,
            0.00459766387939453,
            0.0272567272186279,
            0.00494503974914551,
            0.00505447387695312
          ],
          "obj_and_grad_eval_time_s": [
            0.000168800354003906,
            0.00017237663269043,
            0.00011754035949707,
            0.000116586685180664,
            0.000112295150756836,
            0.000118255615234375,
            0.000184535980224609,
            0.000157594680786133,
            0.000105381011962891,
            0.000102043151855469,
            0.000137805938720703,
            0.000134706497192383,
            0.000108718872070312,
            0.000117301940917969
          ],
          "predict_weight_time": [
            0.0,
            0.0,
            0.0,
            0.0,
            0.0,
            0.0,
            0.0,
            0.0,
            0.0,
            0.0,
            0.0,
            0.0,
            0.0,
            0.0
          ],
          "tf_time_s": [
            6.67572021484375e-05,
            7.2479248046875e-05,
            7.00950622558594e-05,
            5.81741333007812e-05,
            5.7220458984375e-05,
            5.65052032470703e-05,
            6.15119934082031e-05,
            5.31673431396484e-05,
            5.62667846679688e-05,
            5.24520874023438e-05,
            9.89437103271484e-05,
            5.19752502441406e-05,
            6.79492950439453e-05,
            5.38825988769531e-05
          ],
          "tot_obj_time_s": [
            0.0139963626861572,
            0.00680708885192871,
            0.00665402412414551,
            0.00634360313415527,
            0.00611495971679688,
            0.0186865329742432,
            0.00647711753845215,
            0.00622940063476562,
            0.00589895248413086,
            0.0057985782623291,
            0.00564169883728027,
            0.0283586978912354,
            0.00592398643493652,
            0.00605511665344238
          ]
        }
      },
      "lbfgs_iterations": 12,
      "mouse_info": {
        "dragged_pos": [
          0.0,
          0.0,
          0.0
        ],
        "is_dragging": false
      },
      "precondition_time": 0.00146365165710449,
      "tot_step_time_s": 0.130738735198975
    },
    {
      "avg_activated_tets": 31613.8888888889,
      "current_frame": 18,
      "iteration_info": {
        "lbfgs_obj_vals": [
          70.0036679250845,
          44.632553780577,
          56.1322442496146,
          43.0906644231901,
          41.2823757768281,
          40.6935313645104,
          39.7167092146163,
          39.4666135928033,
          39.2678999652353,
          39.2557218452184,
          39.2490208513014,
          39.245479323379,
          39.2449384098083,
          39.244907273735
        ],
        "timing": {
          "energy_forces_time_s": [
            0.000980854034423828,
            0.000895500183105469,
            0.00105071067810059,
            0.000838518142700195,
            0.000894069671630859,
            0.000890016555786133,
            0.000846624374389648,
            0.00087738037109375,
            0.000940084457397461,
            0.000985622406005859,
            0.000890970230102539,
            0.000854253768920898,
            0.000866889953613281,
            0.000921964645385742
          ],
          "linear_decode_time_s": [
            0.00716257095336914,
            0.00569391250610352,
            0.011345386505127,
            0.00948095321655273,
            0.00498270988464355,
            0.00543737411499023,
            0.00534772872924805,
            0.00504779815673828,
            0.0265758037567139,
            0.00544071197509766,
            0.00549626350402832,
            0.00515317916870117,
            0.00524687767028809,
            0.0233809947967529
          ],
          "obj_and_grad_eval_time_s": [
            0.000132083892822266,
            0.000128030776977539,
            0.000122547149658203,
            0.000110387802124023,
            0.000115156173706055,
            0.000105142593383789,
            0.000104188919067383,
            0.000128269195556641,
            0.000127077102661133,
            0.000155210494995117,
            0.000126123428344727,
            0.000134944915771484,
            0.00013422966003418,
            0.000136137008666992
          ],
          "predict_weight_time": [
            0.0,
            0.0,
            0.0,
            0.0,
            0.0,
            0.0,
            0.0,
            0.0,
            0.0,
            0.0,
            0.0,
            0.0,
            0.0,
            0.0
          ],
          "tf_time_s": [
            6.05583190917969e-05,
            8.29696655273438e-05,
            7.91549682617188e-05,
            6.69956207275391e-05,
            6.81877136230469e-05,
            6.58035278320312e-05,
            6.55651092529297e-05,
            6.67572021484375e-05,
            6.27040863037109e-05,
            9.56058502197266e-05,
            8.27312469482422e-05,
            6.17504119873047e-05,
            8.0108642578125e-05,
            5.86509704589844e-05
          ],
          "tot_obj_time_s": [
            0.00833916664123535,
            0.00680375099182129,
            0.012601375579834,
            0.0105001926422119,
            0.00606369972229004,
            0.00650238990783691,
            0.00636672973632812,
            0.00612306594848633,
            0.0277109146118164,
            0.00667929649353027,
            0.00660014152526855,
            0.00620651245117188,
            0.00633120536804199,
            0.0245003700256348
          ]
        }
      },
      "lbfgs_iterations": 12,
      "mouse_info": {
        "dragged_pos": [
          0.0,
          0.0,
          0.0
        ],
        "is_dragging": false
      },
      "precondition_time": 0.00149011611938477,
      "tot_step_time_s": 0.143153190612793
    },
    {
      "avg_activated_tets": 31526.3157894737,
      "current_frame": 19,
      "iteration_info": {
        "lbfgs_obj_vals": [
          75.0840133966386,
          50.2787637531738,
          68.7331058975604,
          49.4718089799972,
          46.5875227993905,
          46.7024769228456,
          45.4480430830074,
          44.8803186203069,
          44.4391312544449,
          44.2398358943795,
          44.2197657164065,
          44.2107512387017,
          44.2052442573579,
          44.2043441437129,
          44.2042814752389
        ],
        "timing": {
          "energy_forces_time_s": [
            0.0011904239654541,
            0.00109410285949707,
            0.00130987167358398,
            0.00104475021362305,
            0.00100159645080566,
            0.000992536544799805,
            0.000938177108764648,
            0.00116539001464844,
            0.00121855735778809,
            0.00111603736877441,
            0.00113415718078613,
            0.000993490219116211,
            0.00113153457641602,
            0.000921010971069336,
            0.00103640556335449
          ],
          "linear_decode_time_s": [
            0.00658082962036133,
            0.00499749183654785,
            0.0264332294464111,
            0.00519204139709473,
            0.00490736961364746,
            0.00446248054504395,
            0.00462007522583008,
            0.0294601917266846,
            0.00704312324523926,
            0.0065312385559082,
            0.0064389705657959,
            0.00551128387451172,
            0.015289306640625,
            0.00591659545898438,
            0.0055851936340332
          ],
          "obj_and_grad_eval_time_s": [
            0.000153303146362305,
            0.00011754035949707,
            0.000216245651245117,
            0.000165939331054688,
            0.000170469284057617,
            0.000159502029418945,
            0.000167131423950195,
            0.000181913375854492,
            0.000173568725585938,
            0.000192880630493164,
            0.000152587890625,
            0.000150203704833984,
            0.000161409378051758,
            0.000149011611938477,
            0.000170469284057617
          ],
          "predict_weight_time": [
            0.0,
            0.0,
            0.0,
            0.0,
            0.0,
            0.0,
            0.0,
            0.0,
            0.0,
            0.0,
            0.0,
            0.0,
            0.0,
            0.0,
            0.0
          ],
          "tf_time_s": [
            5.96046447753906e-05,
            6.74724578857422e-05,
            8.15391540527344e-05,
            7.74860382080078e-05,
            0.000100135803222656,
            7.48634338378906e-05,
            7.03334808349609e-05,
            7.51018524169922e-05,
            0.000105619430541992,
            0.000103235244750977